<?xml version="1.0" encoding="UTF-8"?>
<actor version="1">
  <castshadow/>
  <group>
    <variant>
      <mesh>skeletal/new/m_tunic_short.dae</mesh>
      <props>
        <prop actor="props/units/heads/new/head_corinthian.xml" attachpoint="head"/>
        <prop actor="props/units/weapons/arrow_back.xml" attachpoint="weapon_R"/>
        <prop actor="props/units/weapons/bow_short.xml" attachpoint="weapon_bow"/>
        <prop actor="props/units/quiver_greek_back.xml" attachpoint="back"/>
        <prop actor="props/units/weapons/sheath_xiphos.xml" attachpoint="sheath_02_L"/>
        <prop actor="props/units/capes/cape_med_player_archer.xml" attachpoint="root"/>
      </props>
      <textures>
        <texture file="skeletal/300_athen_themistokles.png" name="baseTex"/>
        <texture file="skeletal/300_spart_spec.png" name="specTex"/>
      </textures>
    </variant>
  </group>
  <group>
    <variant frequency="1" name="Helmet-Corinthians-b4-Iron">
      <props>
        <prop actor="props/units/heads/new/head_hele_a.xml" attachpoint="head"/>
        <prop actor="props/units/helmets/hele_corinthian_b4_iron.xml" attachpoint="helmet"/>
      </props>
    </variant>
  </group>
  <group>
    <variant file="biped/base_archer_relax.xml" name="Archer-Relax" frequency="1"/>
    <variant file="biped/attack_ranged_archer.xml"/>
    <variant file="biped/attack_capture.xml"/>
    <variant file="biped/attack_slaughter.xml"/>
    <variant file="biped/gather_praise.xml"/>
    <variant file="biped/death_cape_long.xml"/>
  </group>
  <material>player_trans_spec.xml</material>
</actor>
